chi42/__init__.py
chi42/chi42.py
chi42-0.3.1.dist-info/METADATA
chi42-0.3.1.dist-info/WHEEL
chi42-0.3.1.dist-info/top_level.txt
chi42-0.3.1.dist-info/RECORD
