Metadata-Version: 2.1
Name: chi42
Version: 0.3.1
Summary: zxczxczxc
Author: asd dasd
Requires-Python: >=3.6
Requires-Dist: pyperclip
